dynprog/VERSION
dynprog/__init__.py
dynprog/sequential.py
dynprog/sequential_func.py
dynprog-0.1.2.dist-info/LICENSE
dynprog-0.1.2.dist-info/METADATA
dynprog-0.1.2.dist-info/WHEEL
dynprog-0.1.2.dist-info/top_level.txt
dynprog-0.1.2.dist-info/RECORD
