Metadata-Version: 2.1
Name: dynprog
Version: 0.1.2
Summary: Generic function for sequential dynamic programming
Home-page: https://github.com/erelsgl/dynprog
Author: Erel Segal-Halevi
Author-email: erelsgl@gmail.com
License: GPL
Project-URL: Bug Reports, https://github.com/erelsgl/dynprog/issues
Project-URL: Source Code, https://github.com/erelsgl/dynprog
Keywords: optimization,dynamic-programming
Platform: UNKNOWN
Classifier: Development Status :: 2 - Pre-Alpha
Requires-Python: >=3.8
License-File: LICENSE
